sqlalchemy_upsert/__init__.py
sqlalchemy_upsert/config.py
sqlalchemy_upsert/main.py
sqlalchemy_upsert-0.1.0.dist-info/LICENSE
sqlalchemy_upsert-0.1.0.dist-info/METADATA
sqlalchemy_upsert-0.1.0.dist-info/WHEEL
sqlalchemy_upsert-0.1.0.dist-info/RECORD
