Metadata-Version: 2.3
Name: sqlalchemy_upsert
Version: 0.1.0
Summary: Upsert helper for PostgreSQL using SQLAlchemy.
License: MIT
Author: Joao Brito
Author-email: machado000@gmail.com
Requires-Python: >=3.9
Classifier: License :: OSI Approved :: MIT License
Classifier: Programming Language :: Python :: 3
Classifier: Programming Language :: Python :: 3.9
Classifier: Programming Language :: Python :: 3.10
Classifier: Programming Language :: Python :: 3.11
Classifier: Programming Language :: Python :: 3.12
Classifier: Programming Language :: Python :: 3.13
Requires-Dist: SQLAlchemy
Requires-Dist: cleantext
Requires-Dist: pandas
Requires-Dist: psycopg2-binary
Requires-Dist: pyodbc
Requires-Dist: python-dotenv
Requires-Dist: tqdm
